Metadata-Version: 2.1
Name: idaly
Version: 1.0.2
Summary: A library and a software that support various algorithms for industrial data augmentation.
Author: chenking
Author-email: 
Keywords: python,industrial data augmentation,data augmentation,windows,mac,linux
Classifier: Development Status :: 1 - Planning
Classifier: Intended Audience :: Developers
Classifier: Programming Language :: Python :: 3
Classifier: Operating System :: Unix
Classifier: Operating System :: MacOS :: MacOS X
Classifier: Operating System :: Microsoft :: Windows
